binding/__init__.py
binding/binding.py
binding-0.3.1.dist-info/LICENSE
binding-0.3.1.dist-info/WHEEL
binding-0.3.1.dist-info/METADATA
binding-0.3.1.dist-info/RECORD
