Metadata-Version: 2.1
Name: binding
Version: 0.3.1
Summary: Bindable properties for Python
Home-page: https://github.com/zauberzeug/binding
License: MIT
Keywords: bind,properties,ui,automatic,values
Author: Zauberzeug GmbH
Author-email: info@zauberzeug.com
Requires-Python: >=3.7,<4.0
Classifier: License :: OSI Approved :: MIT License
Classifier: Programming Language :: Python :: 3
Classifier: Programming Language :: Python :: 3.7
Classifier: Programming Language :: Python :: 3.8
Classifier: Programming Language :: Python :: 3.9
Requires-Dist: executing (>=0.6.0,<0.7.0)
Requires-Dist: forbiddenfruit (>=0.1.4,<0.2.0)
Project-URL: Repository, https://github.com/zauberzeug/binding
